rev/color/__init__.py
rev/color/_init_rev_color.py
rev/color/_rev_color.cpython-36m-x86_64-linux-gnu.so
rev/color/pkgcfg.py
rev/color/revcolor.cpp
rev/color/version.py
rev/color/__pycache__/__init__.cpython-36.pyc
rev/color/__pycache__/_init_rev_color.cpython-36.pyc
rev/color/__pycache__/version.cpython-36.pyc
rev/color/_rev_color/__init__.pyi
rev/color/include/LICENSE.txt
rev/color/include/rev/CIEColor.h
rev/color/include/rev/ColorMatch.h
rev/color/include/rev/ColorSensorV3.h
rev/color/rpy-include/rpygen/rev__ColorSensorV3.hpp
robotpy_rev_color-2021.1.2.0.dist-info/METADATA
robotpy_rev_color-2021.1.2.0.dist-info/WHEEL
robotpy_rev_color-2021.1.2.0.dist-info/entry_points.txt
robotpy_rev_color-2021.1.2.0.dist-info/top_level.txt
robotpy_rev_color-2021.1.2.0.dist-info/RECORD
