Metadata-Version: 2.1
Name: robotpy-rev-color
Version: 2021.1.2.0
Summary: Binary wrapper for REV Color Sensor library
Home-page: https://github.com/robotpy/robotpy-rev-color
Author: RobotPy Development Team
Author-email: robotpy@googlegroups.com
License: BSD-3-Clause
Platform: UNKNOWN
Requires-Python: >=3.6
Requires-Dist: wpilib (<2022.0.0,>=2021.1.2.0)
